.gitignore
CHANGELOG
LICENSE
MANIFEST.in
README.md
setup.py
bin/taskrunner
examples/__init__.py
examples/advanced.py
examples/simple.py
taskrunner/__init__.py
taskrunner/logs.py
taskrunner/main.py
taskrunner.egg-info/PKG-INFO
taskrunner.egg-info/SOURCES.txt
taskrunner.egg-info/dependency_links.txt
taskrunner.egg-info/top_level.txt
tests/test_main.py