Metadata-Version: 1.0
Name: taskrunner
Version: 0.2
Summary: Execute a certain sequence of tasks and later their cleanups in reverse order.
Home-page: http://pypi.python.org/pypi/taskrunner/
Author: Martina Kollarova
Author-email: mkollaro@gmail.com
License: Apache License, Version 2.0
Platform: UNKNOWN
